scale_score/__init__.py
scale_score/eval.py
scale_score/score.py
scale_score/scorer.py
scale_score/utils.py
scale_score-0.1.0.dist-info/METADATA
scale_score-0.1.0.dist-info/WHEEL
scale_score-0.1.0.dist-info/top_level.txt
scale_score-0.1.0.dist-info/RECORD
