Metadata-Version: 2.1
Name: scale-score
Version: 0.1.0
Summary: Implementation of SCALE metric and ScreenEval
Home-page: https://github.com/asappresearch/scale-score
Author: Barrett Lattimer, Patrick Chen, Xinyuan Zhang, Yi Yang
Author-email: blattimer@asapp.com
License: MIT
Keywords: Hallucination detection,Inconsistency detection,hallucination,automatic evaluation,metric,long document,efficient,fast,accurate,long,natural language generation,task agnostic,nlp,nlg
Classifier: Intended Audience :: Science/Research
Classifier: License :: OSI Approved :: MIT License
Classifier: Programming Language :: Python :: 3
Classifier: Topic :: Scientific/Engineering :: Artificial Intelligence
Requires-Python: >=3.6
Requires-Dist: transformers (>=4.21.1)
Requires-Dist: torch (>=1.10.0)
Requires-Dist: numpy (>=1.22.4)
Requires-Dist: tqdm (>=4.64.1)
Requires-Dist: sentencepiece (>=0.1.97)
Requires-Dist: accelerate (>=0.17.1)
Requires-Dist: scikit-learn (>=1.1.3)
Requires-Dist: scipy (>=1.9.3)
